renpy_assets/__init__.py
renpy_assets/cli.py
renpy_assets/commands/__init__.py
renpy_assets/commands/generate.py
renpy_assets/commands/scan.py
renpy_assets/utils/constants.py
renpy_assets/utils/file_utilities.py
renpy_assets-0.1.4.dist-info/METADATA
renpy_assets-0.1.4.dist-info/WHEEL
renpy_assets-0.1.4.dist-info/entry_points.txt
renpy_assets-0.1.4.dist-info/licenses/LICENSE
renpy_assets-0.1.4.dist-info/RECORD
