Metadata-Version: 2.4
Name: renpy-assets
Version: 0.1.4
Summary: CLI tool to scan and manage assets for Ren'Py visual novel projects.
Author: Joseph Evans
License-Expression: MIT
License-File: LICENSE
Requires-Python: >=3.8
Requires-Dist: typer[all]>=0.12.0
